pkg/__init__.py
pkg/crawler.py
pkg/decorator_tools.py
pkg/main.py
pkg/news.py
tests/__init__.py
tests/test_decorator.py
pkg_lomo-0.2.1.dist-info/LICENSE
pkg_lomo-0.2.1.dist-info/METADATA
pkg_lomo-0.2.1.dist-info/WHEEL
pkg_lomo-0.2.1.dist-info/top_level.txt
pkg_lomo-0.2.1.dist-info/RECORD
